{"errors":[],"sptypes":[{"ann":"GHC.Types.Module","ident":"Lib.$trModule","start":{"column":1,"line":1},"stop":{"column":1,"line":1}},{"ann":"GHC.Types.Int -> (GHC.Types.IO (Data.Either.Either Data.Text.Internal.Text (GHC.Types.Int, [GHC.Types.Int])))","ident":"Lib.genARandomPreFactoredNumberLEn","start":{"column":1,"line":20},"stop":{"column":31,"line":20}},{"ann":"GHC.Types.Int","ident":"x","start":{"column":32,"line":20},"stop":{"column":33,"line":20}},{"ann":"{v : GHC.Types.Int | v == x}","ident":"x","start":{"column":36,"line":20},"stop":{"column":37,"line":20}},{"ann":"GHC.Types.Int","ident":"lq_anf$##7205759403792817810","start":{"column":41,"line":20},"stop":{"column":42,"line":20}},{"ann":"(Data.Either.Either Data.Text.Internal.Text (GHC.Types.Int, [GHC.Types.Int])) -> (GHC.Types.IO (Data.Either.Either Data.Text.Internal.Text (GHC.Types.Int, [GHC.Types.Int])))","ident":"_","start":{"column":45,"line":20},"stop":{"column":49,"line":20}},{"ann":"{v : (Data.Either.Either Data.Text.Internal.Text (GHC.Types.Int, [GHC.Types.Int])) | isLeft v}","ident":"_","start":{"column":52,"line":20},"stop":{"column":56,"line":20}},{"ann":"Data.Text.Internal.Text","ident":"lq_anf$##7205759403792817850","start":{"column":59,"line":20},"stop":{"column":73,"line":20}},{"ann":"[GHC.Types.Char]","ident":"lq_anf$##7205759403792817849","start":{"column":64,"line":20},"stop":{"column":73,"line":20}},{"ann":"(Data.Either.Either Data.Text.Internal.Text (GHC.Types.Int, [GHC.Types.Int])) -> (GHC.Types.IO (Data.Either.Either Data.Text.Internal.Text (GHC.Types.Int, [GHC.Types.Int])))","ident":"_","start":{"column":36,"line":21},"stop":{"column":40,"line":21}},{"ann":"{v : (Data.Either.Either Data.Text.Internal.Text (GHC.Types.Int, [GHC.Types.Int])) | not (isLeft v)}","ident":"lq_anf$##7205759403792817847","start":{"column":43,"line":21},"stop":{"column":57,"line":21}},{"ann":"(GHC.Types.Int, [GHC.Types.Int])","ident":"lq_anf$##7205759403792817846","start":{"column":49,"line":21},"stop":{"column":57,"line":21}},{"ann":"GHC.Types.Int","ident":"lq_anf$##7205759403792817841","start":{"column":50,"line":21},"stop":{"column":51,"line":21}},{"ann":"[GHC.Types.Int]","ident":"lq_anf$##7205759403792817845","start":{"column":53,"line":21},"stop":{"column":56,"line":21}},{"ann":"GHC.Types.Int","ident":"lq_anf$##7205759403792817843","start":{"column":54,"line":21},"stop":{"column":55,"line":21}},{"ann":"{v : GHC.Types.Int | v == x}","ident":"x","start":{"column":36,"line":22},"stop":{"column":37,"line":22}},{"ann":"GHC.Types.Int","ident":"lq_anf$##7205759403792817816","start":{"column":41,"line":22},"stop":{"column":42,"line":22}},{"ann":"(Data.Either.Either [GHC.Types.Char] {v : GHC.Types.Int | v /= 0\n                                                          && v > 0\n                                                          && v >= 0\n                                                          && 0 < v\n                                                          && 2 <= v})","ident":"rndM","start":{"column":3,"line":23},"stop":{"column":7,"line":23}},{"ann":"(GHC.Types.IO (Data.Either.Either [GHC.Types.Char] {v : GHC.Types.Int | v /= 0\n                                                                        && v > 0\n                                                                        && v >= 0\n                                                                        && 0 < v\n                                                                        && 2 <= v}))","ident":"_","start":{"column":11,"line":23},"stop":{"column":49,"line":23}},{"ann":"GHC.Types.Int -> (Data.Either.Either [GHC.Types.Char] {v : GHC.Types.Int | 2 <= v})","ident":"RefinementHelper.filterInvalid","start":{"column":16,"line":23},"stop":{"column":29,"line":23}},{"ann":"(GHC.Types.IO GHC.Types.Int)","ident":"lq_anf$##7205759403792817826","start":{"column":30,"line":23},"stop":{"column":49,"line":23}},{"ann":"{v : (GHC.Types.Int, GHC.Types.Int) | snd v == x\n                                      && x_Tuple22 v == x}","ident":"lq_anf$##7205759403792817825","start":{"column":42,"line":23},"stop":{"column":48,"line":23}},{"ann":"GHC.Types.Int","ident":"lq_anf$##7205759403792817824","start":{"column":43,"line":23},"stop":{"column":44,"line":23}},{"ann":"{v : GHC.Types.Int | v == x}","ident":"x","start":{"column":46,"line":23},"stop":{"column":47,"line":23}},{"ann":"{v : (Data.Either.Either [GHC.Types.Char] {v : GHC.Types.Int | v /= 0\n                                                               && v > 0\n                                                               && v >= 0\n                                                               && 0 < v\n                                                               && 2 <= v}) | v == rndM}","ident":"_","start":{"column":8,"line":24},"stop":{"column":12,"line":24}},{"ann":"(Data.Either.Either Data.Text.Internal.Text (GHC.Types.Int, [GHC.Types.Int])) -> (GHC.Types.IO (Data.Either.Either Data.Text.Internal.Text (GHC.Types.Int, [GHC.Types.Int])))","ident":"_","start":{"column":15,"line":25},"stop":{"column":19,"line":25}},{"ann":"{v : (Data.Either.Either Data.Text.Internal.Text (GHC.Types.Int, [GHC.Types.Int])) | isLeft v}","ident":"_","start":{"column":22,"line":25},"stop":{"column":26,"line":25}},{"ann":"Data.Text.Internal.Text","ident":"lq_anf$##7205759403792817830","start":{"column":29,"line":25},"stop":{"column":43,"line":25}},{"ann":"[GHC.Types.Char]","ident":"lq_anf$##7205759403792817829","start":{"column":34,"line":25},"stop":{"column":43,"line":25}},{"ann":"{v : (ShortCircuit.Shortcircuit GHC.Types.Bool) | v == $fShortcircuitBool}","ident":"ShortCircuit.$fShortcircuitBool","start":{"column":20,"line":26},"stop":{"column":87,"line":26}},{"ann":"{v : GHC.Types.Bool | v <=> ps <= x}","ident":"lq_anf$##7205759403792817836","start":{"column":24,"line":26},"stop":{"column":33,"line":26}},{"ann":"{v : GHC.Types.Int | v == ps}","ident":"ps","start":{"column":25,"line":26},"stop":{"column":27,"line":26}},{"ann":"{v : GHC.Types.Int | v == x}","ident":"x","start":{"column":31,"line":26},"stop":{"column":32,"line":26}},{"ann":"(GHC.Types.IO (Data.Either.Either Data.Text.Internal.Text (GHC.Types.Int, [GHC.Types.Int])))","ident":"lq_anf$##7205759403792817838","start":{"column":34,"line":26},"stop":{"column":52,"line":26}},{"ann":"(Data.Either.Either Data.Text.Internal.Text (GHC.Types.Int, [GHC.Types.Int])) -> (GHC.Types.IO (Data.Either.Either Data.Text.Internal.Text (GHC.Types.Int, [GHC.Types.Int])))","ident":"_","start":{"column":35,"line":26},"stop":{"column":39,"line":26}},{"ann":"{v : (Data.Either.Either Data.Text.Internal.Text (GHC.Types.Int, [GHC.Types.Int])) | not (isLeft v)}","ident":"lq_anf$##7205759403792817837","start":{"column":42,"line":26},"stop":{"column":51,"line":26}},{"ann":"{v : (GHC.Types.Int, [GHC.Types.Int]) | v == rsp}","ident":"rsp","start":{"column":48,"line":26},"stop":{"column":51,"line":26}},{"ann":"(GHC.Types.IO (Data.Either.Either Data.Text.Internal.Text (GHC.Types.Int, [GHC.Types.Int])))","ident":"lq_anf$##7205759403792817839","start":{"column":53,"line":26},"stop":{"column":87,"line":26}},{"ann":"{v : GHC.Types.Int | v == x}","ident":"x","start":{"column":85,"line":26},"stop":{"column":86,"line":26}},{"ann":"(GHC.Types.Int, [GHC.Types.Int])","ident":"rsp","start":{"column":9,"line":28},"stop":{"column":12,"line":28}},{"ann":"GHC.Types.Int","ident":"ps","start":{"column":14,"line":28},"stop":{"column":16,"line":28}},{"ann":"{VV : [GHC.Types.Int] | false}","ident":"sq","start":{"column":18,"line":28},"stop":{"column":20,"line":28}},{"ann":"({v : GHC.Types.Int | false}, {v : [GHC.Types.Int] | false})<\\_ VV -> {v : [GHC.Types.Int] | false}>","ident":"lq_anf$##7205759403792817834","start":{"column":24,"line":28},"stop":{"column":53,"line":28}},{"ann":"GHC.Types.Int","ident":"lq_anf$##7205759403792817832","start":{"column":25,"line":28},"stop":{"column":35,"line":28}},{"ann":"{VV : [GHC.Types.Int] | false}","ident":"sq","start":{"column":33,"line":28},"stop":{"column":35,"line":28}},{"ann":"{v : [{v : GHC.Types.Int | v >= 0\n                           && 0 < v}] | 1 <= len v}","ident":"lq_anf$##7205759403792817833","start":{"column":37,"line":28},"stop":{"column":52,"line":28}},{"ann":"{v : GHC.Types.Int | v == upper\n                     && v /= 0\n                     && v > 0\n                     && v >= 0\n                     && 0 < v\n                     && 2 <= v}","ident":"upper","start":{"column":47,"line":28},"stop":{"column":52,"line":28}},{"ann":"(Data.Either.Either Data.Text.Internal.Text (GHC.Types.Int, [GHC.Types.Int])) -> (GHC.Types.IO (Data.Either.Either Data.Text.Internal.Text (GHC.Types.Int, [GHC.Types.Int])))","ident":"_","start":{"column":36,"line":29},"stop":{"column":40,"line":29}},{"ann":"{v : (Data.Either.Either Data.Text.Internal.Text (GHC.Types.Int, [GHC.Types.Int])) | isLeft v}","ident":"_","start":{"column":43,"line":29},"stop":{"column":47,"line":29}},{"ann":"Data.Text.Internal.Text","ident":"lq_anf$##7205759403792817821","start":{"column":50,"line":29},"stop":{"column":64,"line":29}},{"ann":"[GHC.Types.Char]","ident":"lq_anf$##7205759403792817820","start":{"column":55,"line":29},"stop":{"column":64,"line":29}},{"ann":"{VV : GHC.Types.Int | VV >= 0\n                      && 0 < VV} -> {VV : [{VV : GHC.Types.Int | VV >= 0\n                                                                 && 0 < VV}] | 1 <= len VV}","ident":"Lib.createSeq","start":{"column":1,"line":35},"stop":{"column":10,"line":35}},{"ann":"{v : [GHC.Types.Int] | len v == 0}","ident":"lq_anf$##7205759403792817806","start":{"column":15,"line":35},"stop":{"column":18,"line":35}},{"ann":"GHC.Types.Int","ident":"lq_anf$##7205759403792817805","start":{"column":16,"line":35},"stop":{"column":17,"line":35}},{"ann":"{v : GHC.Types.Int | v >= 0\n                     && 0 < v}","ident":"ds_d64T","start":{"column":15,"line":36},"stop":{"column":16,"line":36}},{"ann":"GHC.Types.Int","ident":"lq_anf$##7205759403792817794","start":{"column":20,"line":36},"stop":{"column":21,"line":36}},{"ann":"GHC.Types.Int -> (Data.Either.Either [GHC.Types.Char] {v : GHC.Types.Int | v >= 0\n                                                                           && 0 < v})","ident":"_","start":{"column":29,"line":36},"stop":{"column":48,"line":36}},{"ann":"{v : GHC.Types.Int | v >= 0\n                     && 0 < v}","ident":"lq_anf$##7205759403792817799","start":{"column":51,"line":36},"stop":{"column":65,"line":36}},{"ann":"{v : GHC.Types.Int | v >= 0\n                     && 0 < v}","ident":"ds_d64T","start":{"column":64,"line":36},"stop":{"column":65,"line":36}},{"ann":"{VV : GHC.Types.Int | VV >= 0\n                      && 0 < VV} -> {VV : [{VV : GHC.Types.Int | VV >= 0\n                                                                 && 0 < VV}] | 1 <= len VV}","ident":"Lib.createSeq","start":{"column":13,"line":37},"stop":{"column":24,"line":37}},{"ann":"GHC.Types.Int","ident":"lq_anf$##7205759403792817803","start":{"column":23,"line":37},"stop":{"column":24,"line":37}},{"ann":"{v : GHC.Types.Int | v >= 0\n                     && 0 < v} -> {v : [{v : GHC.Types.Int | v >= 0\n                                                             && 0 < v}] | 1 <= len v}","ident":"Lib.lstPrimesLE","start":{"column":16,"line":38},"stop":{"column":31,"line":38}},{"ann":"{v : GHC.Types.Int | v == okN\n                     && v >= 0\n                     && 0 < v}","ident":"okN","start":{"column":28,"line":38},"stop":{"column":31,"line":38}},{"ann":"{VV : forall a . {v : [GHC.Types.Char] | false} -> a | VV == die}","ident":"RefinementHelper.die","start":{"column":15,"line":39},"stop":{"column":31,"line":39}},{"ann":"[GHC.Types.Char]","ident":"lq_anf$##7205759403792817798","start":{"column":19,"line":39},"stop":{"column":31,"line":39}},{"ann":"{VV : GHC.Types.Int | VV >= 0\n                      && 0 < VV} -> {VV : [{VV : GHC.Types.Int | VV >= 0\n                                                                 && 0 < VV}] | 1 <= len VV}","ident":"Lib.lstPrimesLE","start":{"column":1,"line":43},"stop":{"column":12,"line":43}},{"ann":"{v : [GHC.Types.Int] | len v == 0}","ident":"lq_anf$##7205759403792817776","start":{"column":17,"line":43},"stop":{"column":20,"line":43}},{"ann":"GHC.Types.Int","ident":"lq_anf$##7205759403792817775","start":{"column":18,"line":43},"stop":{"column":19,"line":43}},{"ann":"{v : GHC.Types.Int | v >= 0\n                     && 0 < v}","ident":"ds_d64D","start":{"column":17,"line":44},"stop":{"column":18,"line":44}},{"ann":"GHC.Types.Int","ident":"lq_anf$##7205759403792817755","start":{"column":22,"line":44},"stop":{"column":23,"line":44}},{"ann":"GHC.Types.Int","ident":"lq_anf$##7205759403792817761","start":{"column":26,"line":44},"stop":{"column":27,"line":44}},{"ann":"{v : [{v : GHC.Types.Int | v /= 0\n                           && v > 0\n                           && v >= 0\n                           && 0 < v}] | len v >= 0}","ident":"lq_anf$##7205759403792817773","start":{"column":30,"line":44},"stop":{"column":67,"line":44}},{"ann":"GHC.Types.Int","ident":"ds_d64K","start":{"column":31,"line":44},"stop":{"column":32,"line":44}},{"ann":"[GHC.Types.Int]","ident":"lq_anf$##7205759403792817772","start":{"column":40,"line":44},"stop":{"column":48,"line":44}},{"ann":"GHC.Types.Int","ident":"lq_anf$##7205759403792817771","start":{"column":41,"line":44},"stop":{"column":42,"line":44}},{"ann":"{v : GHC.Types.Int | v >= 0\n                     && 0 < v}","ident":"ds_d64D","start":{"column":46,"line":44},"stop":{"column":47,"line":44}},{"ann":"GHC.Types.Int","ident":"ds_d64K","start":{"column":50,"line":44},"stop":{"column":51,"line":44}},{"ann":"GHC.Types.Int","ident":"lq_anf$##7205759403792817764","start":{"column":54,"line":44},"stop":{"column":55,"line":44}},{"ann":"GHC.Types.Bool","ident":"lq_anf$##7205759403792817767","start":{"column":57,"line":44},"stop":{"column":66,"line":44}},{"ann":"GHC.Types.Int","ident":"ds_d64K","start":{"column":65,"line":44},"stop":{"column":66,"line":44}},{"ann":"{VV : forall a . {v : [GHC.Types.Char] | false} -> a | VV == die}","ident":"RefinementHelper.die","start":{"column":17,"line":45},"stop":{"column":33,"line":45}},{"ann":"[GHC.Types.Char]","ident":"lq_anf$##7205759403792817759","start":{"column":21,"line":45},"stop":{"column":33,"line":45}},{"ann":"{VV : GHC.Types.Int | VV >= 0\n                      && 0 < VV} -> {VV : GHC.Types.Int | VV >= 0\n                                                          && 0 < VV}","ident":"Lib.firstPrimeLE","start":{"column":1,"line":52},"stop":{"column":13,"line":52}},{"ann":"{v : GHC.Prim.Int# | v == 1}","ident":"lq_anf$##7205759403792817790","start":{"column":18,"line":52},"stop":{"column":19,"line":52}},{"ann":"GHC.Types.Bool","ident":"lq_anf$##7205759403792817779","start":{"column":18,"line":53},"stop":{"column":27,"line":53}},{"ann":"{v : GHC.Types.Int | v >= 0\n                     && 0 < v}","ident":"ds_d62Y","start":{"column":26,"line":53},"stop":{"column":27,"line":53}},{"ann":"{v : GHC.Types.Int | v >= 0\n                     && 0 < v}","ident":"ds_d62Y","start":{"column":30,"line":53},"stop":{"column":31,"line":53}},{"ann":"{v : GHC.Types.Int | v >= 0\n                     && 0 < v}","ident":"ds_d62Y","start":{"column":18,"line":54},"stop":{"column":19,"line":54}},{"ann":"GHC.Types.Int","ident":"lq_anf$##7205759403792817782","start":{"column":22,"line":54},"stop":{"column":23,"line":54}},{"ann":"{VV : GHC.Types.Int | VV >= 0\n                      && 0 < VV} -> {VV : GHC.Types.Int | VV >= 0\n                                                          && 0 < VV}","ident":"Lib.firstPrimeLE","start":{"column":26,"line":54},"stop":{"column":46,"line":54}},{"ann":"GHC.Types.Int","ident":"lq_anf$##7205759403792817789","start":{"column":39,"line":54},"stop":{"column":46,"line":54}},{"ann":"{v : GHC.Types.Int | v >= 0\n                     && 0 < v}","ident":"ds_d62Y","start":{"column":40,"line":54},"stop":{"column":41,"line":54}},{"ann":"GHC.Types.Int","ident":"lq_anf$##7205759403792817788","start":{"column":44,"line":54},"stop":{"column":45,"line":54}},{"ann":"{VV : forall a . {v : [GHC.Types.Char] | false} -> a | VV == die}","ident":"RefinementHelper.die","start":{"column":18,"line":55},"stop":{"column":34,"line":55}},{"ann":"[GHC.Types.Char]","ident":"lq_anf$##7205759403792817786","start":{"column":22,"line":55},"stop":{"column":34,"line":55}},{"ann":"({VV : GHC.Types.Int | VV /= 0\n                       && VV > 0\n                       && VV >= 0\n                       && 0 < VV\n                       && 2 <= VV}, {VV : GHC.Types.Int | VV /= 0\n                                                          && VV > 0\n                                                          && VV >= 0\n                                                          && 0 < VV\n                                                          && 2 <= VV})<\\x1 VV -> {VV : GHC.Types.Int | VV /= 0\n                                                                                                       && VV > 0\n                                                                                                       && VV >= 0\n                                                                                                       && VV >= x1\n                                                                                                       && 0 < VV\n                                                                                                       && 2 <= VV}> -> (GHC.Types.IO GHC.Types.Int)","ident":"Lib.getRndMInt","start":{"column":1,"line":60},"stop":{"column":11,"line":60}},{"ann":"{v : (System.Random.Internal.StatefulGen (System.Random.Stateful.AtomicGenM System.Random.Internal.StdGen) GHC.Types.IO) | v == $dStatefulGen_a3yI}","ident":"$dStatefulGen_a3yI","start":{"column":21,"line":60},"stop":{"column":60,"line":60}},{"ann":"{v : (GHC.Types.Int, GHC.Types.Int) | fst v == l\n                                      && snd v == u\n                                      && x_Tuple21 v == l\n                                      && x_Tuple22 v == u}","ident":"lq_anf$##7205759403792817808","start":{"column":31,"line":60},"stop":{"column":37,"line":60}},{"ann":"{v : GHC.Types.Int | v == l\n                     && v /= 0\n                     && v > 0\n                     && v >= 0\n                     && 0 < v\n                     && 2 <= v}","ident":"l","start":{"column":32,"line":60},"stop":{"column":33,"line":60}},{"ann":"{v : GHC.Types.Int | v == u\n                     && v /= 0\n                     && v > 0\n                     && v >= 0\n                     && v >= l\n                     && 0 < v\n                     && 2 <= v}","ident":"u","start":{"column":35,"line":60},"stop":{"column":36,"line":60}},{"ann":"{v : (System.Random.Stateful.AtomicGenM System.Random.Internal.StdGen) | v == globalStdGen}","ident":"System.Random.Stateful.globalStdGen","start":{"column":38,"line":60},"stop":{"column":50,"line":60}}],"status":"safe","types":{"1":{"1":{"ann":"GHC.Types.Module","col":1,"ident":"Lib.$trModule","row":1}},"20":{"1":{"ann":"GHC.Types.Int -> (GHC.Types.IO (Data.Either.Either Data.Text.Internal.Text (GHC.Types.Int, [GHC.Types.Int])))","col":1,"ident":"Lib.genARandomPreFactoredNumberLEn","row":20},"32":{"ann":"GHC.Types.Int","col":32,"ident":"x","row":20},"36":{"ann":"{v : GHC.Types.Int | v == x}","col":36,"ident":"x","row":20},"41":{"ann":"GHC.Types.Int","col":41,"ident":"lq_anf$##7205759403792817810","row":20},"45":{"ann":"(Data.Either.Either Data.Text.Internal.Text (GHC.Types.Int, [GHC.Types.Int])) -> (GHC.Types.IO (Data.Either.Either Data.Text.Internal.Text (GHC.Types.Int, [GHC.Types.Int])))","col":45,"ident":"_","row":20},"52":{"ann":"{v : (Data.Either.Either Data.Text.Internal.Text (GHC.Types.Int, [GHC.Types.Int])) | isLeft v}","col":52,"ident":"_","row":20},"59":{"ann":"Data.Text.Internal.Text","col":59,"ident":"lq_anf$##7205759403792817850","row":20},"64":{"ann":"[GHC.Types.Char]","col":64,"ident":"lq_anf$##7205759403792817849","row":20}},"21":{"36":{"ann":"(Data.Either.Either Data.Text.Internal.Text (GHC.Types.Int, [GHC.Types.Int])) -> (GHC.Types.IO (Data.Either.Either Data.Text.Internal.Text (GHC.Types.Int, [GHC.Types.Int])))","col":36,"ident":"_","row":21},"43":{"ann":"{v : (Data.Either.Either Data.Text.Internal.Text (GHC.Types.Int, [GHC.Types.Int])) | not (isLeft v)}","col":43,"ident":"lq_anf$##7205759403792817847","row":21},"49":{"ann":"(GHC.Types.Int, [GHC.Types.Int])","col":49,"ident":"lq_anf$##7205759403792817846","row":21},"50":{"ann":"GHC.Types.Int","col":50,"ident":"lq_anf$##7205759403792817841","row":21},"53":{"ann":"[GHC.Types.Int]","col":53,"ident":"lq_anf$##7205759403792817845","row":21},"54":{"ann":"GHC.Types.Int","col":54,"ident":"lq_anf$##7205759403792817843","row":21}},"22":{"36":{"ann":"{v : GHC.Types.Int | v == x}","col":36,"ident":"x","row":22},"41":{"ann":"GHC.Types.Int","col":41,"ident":"lq_anf$##7205759403792817816","row":22}},"23":{"11":{"ann":"(GHC.Types.IO (Data.Either.Either [GHC.Types.Char] {v : GHC.Types.Int | v /= 0\n                                                                        && v > 0\n                                                                        && v >= 0\n                                                                        && 0 < v\n                                                                        && 2 <= v}))","col":11,"ident":"_","row":23},"16":{"ann":"GHC.Types.Int -> (Data.Either.Either [GHC.Types.Char] {v : GHC.Types.Int | 2 <= v})","col":16,"ident":"RefinementHelper.filterInvalid","row":23},"3":{"ann":"(Data.Either.Either [GHC.Types.Char] {v : GHC.Types.Int | v /= 0\n                                                          && v > 0\n                                                          && v >= 0\n                                                          && 0 < v\n                                                          && 2 <= v})","col":3,"ident":"rndM","row":23},"30":{"ann":"(GHC.Types.IO GHC.Types.Int)","col":30,"ident":"lq_anf$##7205759403792817826","row":23},"42":{"ann":"{v : (GHC.Types.Int, GHC.Types.Int) | snd v == x\n                                      && x_Tuple22 v == x}","col":42,"ident":"lq_anf$##7205759403792817825","row":23},"43":{"ann":"GHC.Types.Int","col":43,"ident":"lq_anf$##7205759403792817824","row":23},"46":{"ann":"{v : GHC.Types.Int | v == x}","col":46,"ident":"x","row":23}},"24":{"8":{"ann":"{v : (Data.Either.Either [GHC.Types.Char] {v : GHC.Types.Int | v /= 0\n                                                               && v > 0\n                                                               && v >= 0\n                                                               && 0 < v\n                                                               && 2 <= v}) | v == rndM}","col":8,"ident":"_","row":24}},"25":{"15":{"ann":"(Data.Either.Either Data.Text.Internal.Text (GHC.Types.Int, [GHC.Types.Int])) -> (GHC.Types.IO (Data.Either.Either Data.Text.Internal.Text (GHC.Types.Int, [GHC.Types.Int])))","col":15,"ident":"_","row":25},"22":{"ann":"{v : (Data.Either.Either Data.Text.Internal.Text (GHC.Types.Int, [GHC.Types.Int])) | isLeft v}","col":22,"ident":"_","row":25},"29":{"ann":"Data.Text.Internal.Text","col":29,"ident":"lq_anf$##7205759403792817830","row":25},"34":{"ann":"[GHC.Types.Char]","col":34,"ident":"lq_anf$##7205759403792817829","row":25}},"26":{"20":{"ann":"{v : (ShortCircuit.Shortcircuit GHC.Types.Bool) | v == $fShortcircuitBool}","col":20,"ident":"ShortCircuit.$fShortcircuitBool","row":26},"24":{"ann":"{v : GHC.Types.Bool | v <=> ps <= x}","col":24,"ident":"lq_anf$##7205759403792817836","row":26},"25":{"ann":"{v : GHC.Types.Int | v == ps}","col":25,"ident":"ps","row":26},"31":{"ann":"{v : GHC.Types.Int | v == x}","col":31,"ident":"x","row":26},"34":{"ann":"(GHC.Types.IO (Data.Either.Either Data.Text.Internal.Text (GHC.Types.Int, [GHC.Types.Int])))","col":34,"ident":"lq_anf$##7205759403792817838","row":26},"35":{"ann":"(Data.Either.Either Data.Text.Internal.Text (GHC.Types.Int, [GHC.Types.Int])) -> (GHC.Types.IO (Data.Either.Either Data.Text.Internal.Text (GHC.Types.Int, [GHC.Types.Int])))","col":35,"ident":"_","row":26},"42":{"ann":"{v : (Data.Either.Either Data.Text.Internal.Text (GHC.Types.Int, [GHC.Types.Int])) | not (isLeft v)}","col":42,"ident":"lq_anf$##7205759403792817837","row":26},"48":{"ann":"{v : (GHC.Types.Int, [GHC.Types.Int]) | v == rsp}","col":48,"ident":"rsp","row":26},"53":{"ann":"(GHC.Types.IO (Data.Either.Either Data.Text.Internal.Text (GHC.Types.Int, [GHC.Types.Int])))","col":53,"ident":"lq_anf$##7205759403792817839","row":26},"85":{"ann":"{v : GHC.Types.Int | v == x}","col":85,"ident":"x","row":26}},"28":{"14":{"ann":"GHC.Types.Int","col":14,"ident":"ps","row":28},"18":{"ann":"{VV : [GHC.Types.Int] | false}","col":18,"ident":"sq","row":28},"24":{"ann":"({v : GHC.Types.Int | false}, {v : [GHC.Types.Int] | false})<\\_ VV -> {v : [GHC.Types.Int] | false}>","col":24,"ident":"lq_anf$##7205759403792817834","row":28},"25":{"ann":"GHC.Types.Int","col":25,"ident":"lq_anf$##7205759403792817832","row":28},"33":{"ann":"{VV : [GHC.Types.Int] | false}","col":33,"ident":"sq","row":28},"37":{"ann":"{v : [{v : GHC.Types.Int | v >= 0\n                           && 0 < v}] | 1 <= len v}","col":37,"ident":"lq_anf$##7205759403792817833","row":28},"47":{"ann":"{v : GHC.Types.Int | v == upper\n                     && v /= 0\n                     && v > 0\n                     && v >= 0\n                     && 0 < v\n                     && 2 <= v}","col":47,"ident":"upper","row":28},"9":{"ann":"(GHC.Types.Int, [GHC.Types.Int])","col":9,"ident":"rsp","row":28}},"29":{"36":{"ann":"(Data.Either.Either Data.Text.Internal.Text (GHC.Types.Int, [GHC.Types.Int])) -> (GHC.Types.IO (Data.Either.Either Data.Text.Internal.Text (GHC.Types.Int, [GHC.Types.Int])))","col":36,"ident":"_","row":29},"43":{"ann":"{v : (Data.Either.Either Data.Text.Internal.Text (GHC.Types.Int, [GHC.Types.Int])) | isLeft v}","col":43,"ident":"_","row":29},"50":{"ann":"Data.Text.Internal.Text","col":50,"ident":"lq_anf$##7205759403792817821","row":29},"55":{"ann":"[GHC.Types.Char]","col":55,"ident":"lq_anf$##7205759403792817820","row":29}},"35":{"1":{"ann":"{VV : GHC.Types.Int | VV >= 0\n                      && 0 < VV} -> {VV : [{VV : GHC.Types.Int | VV >= 0\n                                                                 && 0 < VV}] | 1 <= len VV}","col":1,"ident":"Lib.createSeq","row":35},"15":{"ann":"{v : [GHC.Types.Int] | len v == 0}","col":15,"ident":"lq_anf$##7205759403792817806","row":35},"16":{"ann":"GHC.Types.Int","col":16,"ident":"lq_anf$##7205759403792817805","row":35}},"36":{"15":{"ann":"{v : GHC.Types.Int | v >= 0\n                     && 0 < v}","col":15,"ident":"ds_d64T","row":36},"20":{"ann":"GHC.Types.Int","col":20,"ident":"lq_anf$##7205759403792817794","row":36},"29":{"ann":"GHC.Types.Int -> (Data.Either.Either [GHC.Types.Char] {v : GHC.Types.Int | v >= 0\n                                                                           && 0 < v})","col":29,"ident":"_","row":36},"51":{"ann":"{v : GHC.Types.Int | v >= 0\n                     && 0 < v}","col":51,"ident":"lq_anf$##7205759403792817799","row":36},"64":{"ann":"{v : GHC.Types.Int | v >= 0\n                     && 0 < v}","col":64,"ident":"ds_d64T","row":36}},"37":{"13":{"ann":"{VV : GHC.Types.Int | VV >= 0\n                      && 0 < VV} -> {VV : [{VV : GHC.Types.Int | VV >= 0\n                                                                 && 0 < VV}] | 1 <= len VV}","col":13,"ident":"Lib.createSeq","row":37},"23":{"ann":"GHC.Types.Int","col":23,"ident":"lq_anf$##7205759403792817803","row":37}},"38":{"16":{"ann":"{v : GHC.Types.Int | v >= 0\n                     && 0 < v} -> {v : [{v : GHC.Types.Int | v >= 0\n                                                             && 0 < v}] | 1 <= len v}","col":16,"ident":"Lib.lstPrimesLE","row":38},"28":{"ann":"{v : GHC.Types.Int | v == okN\n                     && v >= 0\n                     && 0 < v}","col":28,"ident":"okN","row":38}},"39":{"15":{"ann":"{VV : forall a . {v : [GHC.Types.Char] | false} -> a | VV == die}","col":15,"ident":"RefinementHelper.die","row":39},"19":{"ann":"[GHC.Types.Char]","col":19,"ident":"lq_anf$##7205759403792817798","row":39}},"43":{"1":{"ann":"{VV : GHC.Types.Int | VV >= 0\n                      && 0 < VV} -> {VV : [{VV : GHC.Types.Int | VV >= 0\n                                                                 && 0 < VV}] | 1 <= len VV}","col":1,"ident":"Lib.lstPrimesLE","row":43},"17":{"ann":"{v : [GHC.Types.Int] | len v == 0}","col":17,"ident":"lq_anf$##7205759403792817776","row":43},"18":{"ann":"GHC.Types.Int","col":18,"ident":"lq_anf$##7205759403792817775","row":43}},"44":{"17":{"ann":"{v : GHC.Types.Int | v >= 0\n                     && 0 < v}","col":17,"ident":"ds_d64D","row":44},"22":{"ann":"GHC.Types.Int","col":22,"ident":"lq_anf$##7205759403792817755","row":44},"26":{"ann":"GHC.Types.Int","col":26,"ident":"lq_anf$##7205759403792817761","row":44},"30":{"ann":"{v : [{v : GHC.Types.Int | v /= 0\n                           && v > 0\n                           && v >= 0\n                           && 0 < v}] | len v >= 0}","col":30,"ident":"lq_anf$##7205759403792817773","row":44},"31":{"ann":"GHC.Types.Int","col":31,"ident":"ds_d64K","row":44},"40":{"ann":"[GHC.Types.Int]","col":40,"ident":"lq_anf$##7205759403792817772","row":44},"41":{"ann":"GHC.Types.Int","col":41,"ident":"lq_anf$##7205759403792817771","row":44},"46":{"ann":"{v : GHC.Types.Int | v >= 0\n                     && 0 < v}","col":46,"ident":"ds_d64D","row":44},"50":{"ann":"GHC.Types.Int","col":50,"ident":"ds_d64K","row":44},"54":{"ann":"GHC.Types.Int","col":54,"ident":"lq_anf$##7205759403792817764","row":44},"57":{"ann":"GHC.Types.Bool","col":57,"ident":"lq_anf$##7205759403792817767","row":44},"65":{"ann":"GHC.Types.Int","col":65,"ident":"ds_d64K","row":44}},"45":{"17":{"ann":"{VV : forall a . {v : [GHC.Types.Char] | false} -> a | VV == die}","col":17,"ident":"RefinementHelper.die","row":45},"21":{"ann":"[GHC.Types.Char]","col":21,"ident":"lq_anf$##7205759403792817759","row":45}},"52":{"1":{"ann":"{VV : GHC.Types.Int | VV >= 0\n                      && 0 < VV} -> {VV : GHC.Types.Int | VV >= 0\n                                                          && 0 < VV}","col":1,"ident":"Lib.firstPrimeLE","row":52},"18":{"ann":"{v : GHC.Prim.Int# | v == 1}","col":18,"ident":"lq_anf$##7205759403792817790","row":52}},"53":{"18":{"ann":"GHC.Types.Bool","col":18,"ident":"lq_anf$##7205759403792817779","row":53},"26":{"ann":"{v : GHC.Types.Int | v >= 0\n                     && 0 < v}","col":26,"ident":"ds_d62Y","row":53},"30":{"ann":"{v : GHC.Types.Int | v >= 0\n                     && 0 < v}","col":30,"ident":"ds_d62Y","row":53}},"54":{"18":{"ann":"{v : GHC.Types.Int | v >= 0\n                     && 0 < v}","col":18,"ident":"ds_d62Y","row":54},"22":{"ann":"GHC.Types.Int","col":22,"ident":"lq_anf$##7205759403792817782","row":54},"26":{"ann":"{VV : GHC.Types.Int | VV >= 0\n                      && 0 < VV} -> {VV : GHC.Types.Int | VV >= 0\n                                                          && 0 < VV}","col":26,"ident":"Lib.firstPrimeLE","row":54},"39":{"ann":"GHC.Types.Int","col":39,"ident":"lq_anf$##7205759403792817789","row":54},"40":{"ann":"{v : GHC.Types.Int | v >= 0\n                     && 0 < v}","col":40,"ident":"ds_d62Y","row":54},"44":{"ann":"GHC.Types.Int","col":44,"ident":"lq_anf$##7205759403792817788","row":54}},"55":{"18":{"ann":"{VV : forall a . {v : [GHC.Types.Char] | false} -> a | VV == die}","col":18,"ident":"RefinementHelper.die","row":55},"22":{"ann":"[GHC.Types.Char]","col":22,"ident":"lq_anf$##7205759403792817786","row":55}},"60":{"1":{"ann":"({VV : GHC.Types.Int | VV /= 0\n                       && VV > 0\n                       && VV >= 0\n                       && 0 < VV\n                       && 2 <= VV}, {VV : GHC.Types.Int | VV /= 0\n                                                          && VV > 0\n                                                          && VV >= 0\n                                                          && 0 < VV\n                                                          && 2 <= VV})<\\x1 VV -> {VV : GHC.Types.Int | VV /= 0\n                                                                                                       && VV > 0\n                                                                                                       && VV >= 0\n                                                                                                       && VV >= x1\n                                                                                                       && 0 < VV\n                                                                                                       && 2 <= VV}> -> (GHC.Types.IO GHC.Types.Int)","col":1,"ident":"Lib.getRndMInt","row":60},"21":{"ann":"{v : (System.Random.Internal.StatefulGen (System.Random.Stateful.AtomicGenM System.Random.Internal.StdGen) GHC.Types.IO) | v == $dStatefulGen_a3yI}","col":21,"ident":"$dStatefulGen_a3yI","row":60},"31":{"ann":"{v : (GHC.Types.Int, GHC.Types.Int) | fst v == l\n                                      && snd v == u\n                                      && x_Tuple21 v == l\n                                      && x_Tuple22 v == u}","col":31,"ident":"lq_anf$##7205759403792817808","row":60},"32":{"ann":"{v : GHC.Types.Int | v == l\n                     && v /= 0\n                     && v > 0\n                     && v >= 0\n                     && 0 < v\n                     && 2 <= v}","col":32,"ident":"l","row":60},"35":{"ann":"{v : GHC.Types.Int | v == u\n                     && v /= 0\n                     && v > 0\n                     && v >= 0\n                     && v >= l\n                     && 0 < v\n                     && 2 <= v}","col":35,"ident":"u","row":60},"38":{"ann":"{v : (System.Random.Stateful.AtomicGenM System.Random.Internal.StdGen) | v == globalStdGen}","col":38,"ident":"System.Random.Stateful.globalStdGen","row":60}}}}